tinysemver/__init__.py
tinysemver/tinysemver.py
tinysemver-3.0.0.dist-info/licenses/LICENSE
tinysemver-3.0.0.dist-info/METADATA
tinysemver-3.0.0.dist-info/WHEEL
tinysemver-3.0.0.dist-info/entry_points.txt
tinysemver-3.0.0.dist-info/top_level.txt
tinysemver-3.0.0.dist-info/RECORD
