Metadata-Version: 2.4
Name: tinysemver
Version: 3.0.0
Summary: Semantic-Versioning... that doesn't need 300,000 lines of JS
Author-email: Ash Vardanian <1983160+ashvardanian@users.noreply.github.com>
License:                                  Apache License
Project-URL: Homepage, https://pypi.org/project/tinysemver/
Project-URL: Documentation, https://github.com/ashvardanian/TinySemVer/blob/main/README.md
Project-URL: Repository, https://github.com/ashvardanian/TinySemVer.git
Project-URL: Issues, https://github.com/ashvardanian/TinySemVer/issues
Project-URL: Changelog, https://github.com/ashvardanian/TinySemVer/blob/main/CHANGELOG.md
Classifier: Development Status :: 5 - Production/Stable
Classifier: Intended Audience :: Developers
Classifier: Topic :: Software Development :: Build Tools
Classifier: License :: OSI Approved :: Apache Software License
Classifier: Programming Language :: Python :: 3
Classifier: Programming Language :: Python :: 3.6
Classifier: Programming Language :: Python :: 3.7
Classifier: Programming Language :: Python :: 3.8
Classifier: Programming Language :: Python :: 3.9
Classifier: Programming Language :: Python :: 3.10
Classifier: Programming Language :: Python :: 3.11
License-File: LICENSE
Requires-Dist: rich>=13.8.0
Provides-Extra: test
Requires-Dist: pytest>=7.0.0; extra == "test"
Requires-Dist: pytest-cov>=4.0.0; extra == "test"
Requires-Dist: pytest-mock>=3.10.0; extra == "test"
Provides-Extra: dev
Requires-Dist: pytest>=7.0.0; extra == "dev"
Requires-Dist: pytest-cov>=4.0.0; extra == "dev"
Requires-Dist: pytest-mock>=3.10.0; extra == "dev"
Requires-Dist: ruff>=0.1.0; extra == "dev"
Requires-Dist: mypy>=1.0.0; extra == "dev"
Requires-Dist: black>=23.0.0; extra == "dev"
Dynamic: license-file
